{
 "actions": [],
 "allow_rename": 1,
 "creation": "2024-07-23 17:21:37.331873",
 "doctype": "DocType",
 "editable_grid": 1,
 "engine": "InnoDB",
 "field_order": [
  "stages_of_project",
  "activities",
  "section_break_bovu",
  "l1",
  "l3",
  "column_break_efoc",
  "l2",
  "l4",
  "total_days",
  "section_break_tfta",
  "l1_hours",
  "l4_hours",
  "column_break_disa",
  "l3_hours",
  "l2_hours",
  "total_hoursday"
 ],
 "fields": [
  {
   "fieldname": "stages_of_project",
   "fieldtype": "Link",
   "in_list_view": 1,
   "label": "Stages of Project",
   "options": "Task"
  },
  {
   "fieldname": "activities",
   "fieldtype": "Link",
   "in_list_view": 1,
   "label": "Activities",
   "options": "Task"
  },
  {
   "fieldname": "section_break_bovu",
   "fieldtype": "Section Break",
   "label": "Days"
  },
  {
   "fieldname": "l1",
   "fieldtype": "Float",
   "in_list_view": 1,
   "label": "L1 Days"
  },
  {
   "fieldname": "l3",
   "fieldtype": "Float",
   "in_list_view": 1,
   "label": "L3 Days"
  },
  {
   "fieldname": "column_break_efoc",
   "fieldtype": "Column Break"
  },
  {
   "fieldname": "l2",
   "fieldtype": "Float",
   "in_list_view": 1,
   "label": "L2 Days"
  },
  {
   "fieldname": "l4",
   "fieldtype": "Float",
   "in_list_view": 1,
   "label": "L4 Days"
  },
  {
   "fieldname": "total_days",
   "fieldtype": "Float",
   "in_list_view": 1,
   "label": "Total Days"
  },
  {
   "fieldname": "section_break_tfta",
   "fieldtype": "Section Break",
   "label": "Hours/ Day"
  },
  {
   "fieldname": "l1_hours",
   "fieldtype": "Float",
   "label": "L1 Hours"
  },
  {
   "fieldname": "l4_hours",
   "fieldtype": "Float",
   "label": "L4 Hours "
  },
  {
   "fieldname": "column_break_disa",
   "fieldtype": "Column Break"
  },
  {
   "fieldname": "l3_hours",
   "fieldtype": "Float",
   "label": "L3 Hours "
  },
  {
   "fieldname": "l2_hours",
   "fieldtype": "Float",
   "label": "L2 Hours "
  },
  {
   "fieldname": "total_hoursday",
   "fieldtype": "Float",
   "label": "Total Hours/Day"
  }
 ],
 "index_web_pages_for_search": 1,
 "istable": 1,
 "links": [],
 "modified": "2024-08-07 10:39:12.635122",
 "modified_by": "Administrator",
 "module": "Envision CRM",
 "name": "Man Days",
 "owner": "Administrator",
 "permissions": [],
 "sort_field": "modified",
 "sort_order": "DESC",
 "states": []
}